pyspainmobility/__init__.py
pyspainmobility/mobility/__init__.py
pyspainmobility/mobility/mobility.py
pyspainmobility/utils/__init__.py
pyspainmobility/utils/utils.py
pyspainmobility/zones/__init__.py
pyspainmobility/zones/zones.py
pyspainmobility-1.0.4.dist-info/licenses/LICENSE
pyspainmobility-1.0.4.dist-info/METADATA
pyspainmobility-1.0.4.dist-info/WHEEL
pyspainmobility-1.0.4.dist-info/top_level.txt
pyspainmobility-1.0.4.dist-info/RECORD
