Metadata-Version: 2.4
Name: pyspainmobility
Version: 1.0.4
Summary: Library for downloading and processing Spanish mobility data from MITMA
Home-page: https://github.com/pySpainMobility/pySpainMobility
Author: Massimiliano Luca
Author-email: mluca@fbk.eu
License: BSD 3-Clause License
Classifier: Programming Language :: Python :: 3
Classifier: License :: OSI Approved :: BSD License
Classifier: Operating System :: OS Independent
Requires-Python: >=3.9
License-File: LICENSE
Requires-Dist: geopandas~=1.0.1
Requires-Dist: tqdm>=4.0.0
Requires-Dist: matplotlib>=3.0.0
Requires-Dist: pyarrow>=8.0.0
Requires-Dist: dask[dataframe]>=2024.0
Provides-Extra: docs
Requires-Dist: Sphinx>=4.0.0; extra == "docs"
Requires-Dist: furo; extra == "docs"
Requires-Dist: sphinx-autodoc-typehints; extra == "docs"
Requires-Dist: sphinxcontrib-napoleon; extra == "docs"
Provides-Extra: dev
Requires-Dist: pytest>=6.0; extra == "dev"
Requires-Dist: flake8; extra == "dev"
Dynamic: author
Dynamic: author-email
Dynamic: classifier
Dynamic: description
Dynamic: description-content-type
Dynamic: home-page
Dynamic: license
Dynamic: license-file
Dynamic: provides-extra
Dynamic: requires-dist
Dynamic: requires-python
Dynamic: summary
